djangocms_mdeditor/__init__.py
djangocms_mdeditor/admin.py
djangocms_mdeditor/apps.py
djangocms_mdeditor/cms_plugins.py
djangocms_mdeditor/fields.py
djangocms_mdeditor/models.py
djangocms_mdeditor/widgets.py
djangocms_mdeditor/migrations/0001_initial.py
djangocms_mdeditor/migrations/__init__.py
djangocms_mdeditor/static/css/ace-djangocms-fix.min.css
djangocms_mdeditor/templates/render_text_plugin.html
djangocms_mdeditor-0.1.0.dist-info/LICENSE
djangocms_mdeditor-0.1.0.dist-info/METADATA
djangocms_mdeditor-0.1.0.dist-info/WHEEL
djangocms_mdeditor-0.1.0.dist-info/top_level.txt
djangocms_mdeditor-0.1.0.dist-info/RECORD
