Metadata-Version: 2.1
Name: djangocms-mdeditor
Version: 0.1.0
Summary: Text Plugin for django CMS using Martor for Markdown-enabled text-editing.
Home-page: https://github.com/danniranderis/djangocms-mdeditor
Author: Danni Randeris
Author-email: danni@danniranderis.dk
License: MIT
Download-URL: https://github.com/danniranderis/djangocms-mdeditor/tarball/v0.1.0
Keywords: python,markdown,django,addon,django-cms
Platform: UNKNOWN
Classifier: Development Status :: 5 - Production/Stable
Classifier: Environment :: Web Environment
Classifier: Intended Audience :: Developers
Classifier: License :: OSI Approved :: MIT License
Classifier: Operating System :: OS Independent
Classifier: Programming Language :: Python :: 3
Classifier: Programming Language :: Python :: 3.6
Classifier: Programming Language :: Python :: 3.7
Classifier: Programming Language :: Python :: 3.8
Classifier: Programming Language :: Python :: 3.9
Classifier: Programming Language :: Python :: 3 :: Only
Classifier: Framework :: Django
Classifier: Framework :: Django :: 3.1
Classifier: Framework :: Django :: 3.2
Classifier: Framework :: Django CMS
Classifier: Topic :: Internet :: WWW/HTTP
Classifier: Topic :: Internet :: WWW/HTTP :: Dynamic Content
Classifier: Topic :: Software Development
Classifier: Topic :: Software Development :: Libraries
Requires-Python: >=3.6
Requires-Dist: django-cms (>=3.9)
Requires-Dist: martor (>=1.6.4)
